mlsimplified/__init__.py
mlsimplified/model.py
mlsimplified-1.0.0.dist-info/licenses/LICENSE
mlsimplified-1.0.0.dist-info/METADATA
mlsimplified-1.0.0.dist-info/WHEEL
mlsimplified-1.0.0.dist-info/top_level.txt
mlsimplified-1.0.0.dist-info/RECORD
